memas_client/__init__.py
memas_client/api_client.py
memas_client/configuration.py
memas_client/exceptions.py
memas_client/rest.py
memas_client/schemas.py
memas_client/apis/__init__.py
memas_client/apis/path_to_api.py
memas_client/apis/tag_to_api.py
memas_client/apis/paths/__init__.py
memas_client/apis/paths/dp_memorize.py
memas_client/apis/paths/dp_recall.py
memas_client/apis/tags/__init__.py
memas_client/apis/tags/dp_api.py
memas_client/model/__init__.py
memas_client/model/citation.py
memas_client/model/cited_document.py
memas_client/model/corpus_pathname.py
memas_client/model/namespace_pathname.py
memas_client/models/__init__.py
memas_client/paths/__init__.py
memas_client/paths/dp_memorize/__init__.py
memas_client/paths/dp_memorize/post.py
memas_client/paths/dp_recall/__init__.py
memas_client/paths/dp_recall/post.py
memas_client-0.1.3.dist-info/LICENSE
memas_client-0.1.3.dist-info/METADATA
memas_client-0.1.3.dist-info/WHEEL
memas_client-0.1.3.dist-info/top_level.txt
memas_client-0.1.3.dist-info/RECORD
