Metadata-Version: 2.1
Name: memas-client
Version: 0.1.3
Summary: MeMaS DP APIs
Home-page: https://github.com/memas-ai/MeMaS-python-client
Author: OpenAPI Generator community
Author-email: max.yu@memas.ai
License: Apache 2.0
Keywords: OpenAPI,OpenAPI-Generator,MeMaS DP APIs
Requires-Python: >=3.7
License-File: LICENSE
Requires-Dist: certifi >=14.5.14
Requires-Dist: frozendict ~=2.3.4
Requires-Dist: python-dateutil <3.0.0,>=2.7.0
Requires-Dist: setuptools >=21.0.0
Requires-Dist: typing-extensions >=4.3.0
Requires-Dist: urllib3 ~=1.26.7
